#######################################################################################################################################
<fanart>https://www.laserdisken.dk/billeder/forsidestor/1194952147707710.jpg</fanart>
#######################################################################################################################################

<item>
<title>[COLOR yellow][B]Rapporter fejl og tilmeld nyhedsmail til:[/B][/COLOR] [COLOR red] dksek@protonmail.com[/COLOR]</title>
<link></link>
<thumbnail>blogs.uladech.edu.pe/pastillasgerenciales/wp-content/uploads/sites/18/2016/08/error-code-18.jpeg</thumbnail>
</item>

<item>
<title>Afsnit 1</title>
<link>http://vk.com/video397507268_456239631</link>
<thumbnail>https://www.laserdisken.dk/billeder/forsidestor/1194952147707710.jpg</thumbnail>
</item>

<item>
<title>Afsnit 2</title>
<link>http://vk.com/video397507268_456239632</link>
<thumbnail>https://www.laserdisken.dk/billeder/forsidestor/1194952147707710.jpg</thumbnail>
</item>

<item>
<title>Afsnit 3</title>
<link>http://vk.com/video397507268_456239633</link>
<thumbnail>https://www.laserdisken.dk/billeder/forsidestor/1194952147707710.jpg</thumbnail>
</item>

<item>
<title>Afsnit 4</title>
<link>http://vk.com/video397507268_456239634</link>
<thumbnail>https://www.laserdisken.dk/billeder/forsidestor/1194952147707710.jpg</thumbnail>
</item>

<item>
<title>Afsnit 5</title>
<link>http://vk.com/video397507268_456239635</link>
<thumbnail>https://www.laserdisken.dk/billeder/forsidestor/1194952147707710.jpg</thumbnail>
</item>

<item>
<title>Afsnit 6</title>
<link>http://vk.com/video397507268_456239636</link>
<thumbnail>https://www.laserdisken.dk/billeder/forsidestor/1194952147707710.jpg</thumbnail>
</item>

<item>
<title>Afsnit 7</title>
<link>http://vk.com/video397507268_456239637</link>
<thumbnail>https://www.laserdisken.dk/billeder/forsidestor/1194952147707710.jpg</thumbnail>
</item>

<item>
<title>Afsnit 8</title>
<link>http://vk.com/video397507268_456239638</link>
<thumbnail>https://www.laserdisken.dk/billeder/forsidestor/1194952147707710.jpg</thumbnail>
</item>

<item>
<title>Afsnit 9</title>
<link>http://vk.com/video397507268_456239639</link>
<thumbnail>https://www.laserdisken.dk/billeder/forsidestor/1194952147707710.jpg</thumbnail>
</item>

<item>
<title>Afsnit 10</title>
<link>http://vk.com/video397507268_456239640</link>
<thumbnail>https://www.laserdisken.dk/billeder/forsidestor/1194952147707710.jpg</thumbnail>
</item>

<item>
<title>Afsnit 11</title>
<link>http://vk.com/video397507268_456239641</link>
<thumbnail>https://www.laserdisken.dk/billeder/forsidestor/1194952147707710.jpg</thumbnail>
</item>

<item>
<title>Afsnit 12</title>
<link>http://vk.com/video397507268_456239642</link>
<thumbnail>https://www.laserdisken.dk/billeder/forsidestor/1194952147707710.jpg</thumbnail>
</item>

<item>
<title>Afsnit 13</title>
<link>http://vk.com/video397507268_456239643</link>
<thumbnail>https://www.laserdisken.dk/billeder/forsidestor/1194952147707710.jpg</thumbnail>
</item>

<item>
<title>Afsnit 14</title>
<link>http://vk.com/video397507268_456239644</link>
<thumbnail>https://www.laserdisken.dk/billeder/forsidestor/1194952147707710.jpg</thumbnail>
</item>

<item>
<title>Afsnit 15</title>
<link>http://vk.com/video397507268_456239645</link>
<thumbnail>https://www.laserdisken.dk/billeder/forsidestor/1194952147707710.jpg</thumbnail>
</item>

<item>
<title>Afsnit 16</title>
<link>http://vk.com/video397507268_456239646</link>
<thumbnail>https://www.laserdisken.dk/billeder/forsidestor/1194952147707710.jpg</thumbnail>
</item>

<item>
<title>Afsnit 17</title>
<link>http://vk.com/video397507268_456239647</link>
<thumbnail>https://www.laserdisken.dk/billeder/forsidestor/1194952147707710.jpg</thumbnail>
</item>

<item>
<title>Afsnit 18</title>
<link>http://vk.com/video397507268_456239648</link>
<thumbnail>https://www.laserdisken.dk/billeder/forsidestor/1194952147707710.jpg</thumbnail>
</item>

<item>
<title>Afsnit 19</title>
<link>http://vk.com/video397507268_456239649</link>
<thumbnail>https://www.laserdisken.dk/billeder/forsidestor/1194952147707710.jpg</thumbnail>
</item>

<item>
<title>Afsnit 20</title>
<link>http://vk.com/video397507268_456239650</link>
<thumbnail>https://www.laserdisken.dk/billeder/forsidestor/1194952147707710.jpg</thumbnail>
</item>

<item>
<title>Afsnit 21</title>
<link>http://vk.com/video397507268_456239651</link>
<thumbnail>https://www.laserdisken.dk/billeder/forsidestor/1194952147707710.jpg</thumbnail>
</item>

<item>
<title>Afsnit 22</title>
<link>http://vk.com/video397507268_456239655</link>
<thumbnail>https://www.laserdisken.dk/billeder/forsidestor/1194952147707710.jpg</thumbnail>
</item>

<item>
<title>Afsnit 23</title>
<link>http://vk.com/video397507268_456239653</link>
<thumbnail>https://www.laserdisken.dk/billeder/forsidestor/1194952147707710.jpg</thumbnail>
</item>

<item>
<title>Afsnit 24</title>
<link>http://vk.com/video397507268_456239654</link>
<thumbnail>https://www.laserdisken.dk/billeder/forsidestor/1194952147707710.jpg</thumbnail>
</item>
